PyLab/__init__.py
PyLab/argparser.py
PyLab/device.py
PyLab/logger.py
PyLab/vars.py
PyLab/image/CAM_nncam.py
PyLab/image/CAM_ueye.py
PyLab/image/SLM_casmi.py
PyLab/image/SLM_holoeye.py
PyLab/image/__init__.py
PyLab/image/cam_files/__init__.py
PyLab/image/cam_files/nncam.dll
PyLab/image/cam_files/nncam.lib
PyLab/image/cam_files/nncam.py
PyLab/image/slm_files/__init__.py
PyLab/image/slm_files/showSLMPreview.py
PyLab/measure/ItechIt6322.py
PyLab/measure/Keysight34970A.py
PyLab/measure/Rigol3058E.py
PyLab/measure/RigolDG822.py
PyLab/measure/SCPIDevice.py
PyLab/measure/SampleDevice.py
PyLab/measure/TektronixMSO2024B.py
PyLab/measure/__init__.py
PyLab/measure/utils.py
PyLab/measure/ThorlabsPM100/ThorlabsPM100.py
PyLab/measure/ThorlabsPM100/VISA_wrapper_metaclass.py
PyLab/measure/ThorlabsPM100/__init__.py
PyLab/measure/ThorlabsPM100/usbtmc.py
PyLab/measure/ThorlabsPM100/test/__init__.py
PyLab/measure/ThorlabsPM100/test/test_thorlabsPM100.py
PyLab/others/__init__.py
PyLab/others/fei_text.py
PyLab/others/im_for_OP1.py
PyLab/others/move_udp.py
alphacenlab-0.1.8.dist-info/LICENSE.txt
alphacenlab-0.1.8.dist-info/METADATA
alphacenlab-0.1.8.dist-info/WHEEL
alphacenlab-0.1.8.dist-info/top_level.txt
alphacenlab-0.1.8.dist-info/RECORD
