Metadata-Version: 2.1
Name: alphacenlab
Version: 0.1.8
Summary: pylab code for alphacen.
Home-page: https://git.alphacen.co/muwei/Lab_Automation
Author: Muwei Zhang
Author-email: muwei@alphacen.io
License: MIT
Platform: UNKNOWN
Classifier: License :: OSI Approved :: MIT License
Classifier: Programming Language :: Python
Classifier: Programming Language :: Python :: 3
Classifier: Programming Language :: Python :: 3.6
Classifier: Programming Language :: Python :: Implementation :: CPython
Classifier: Programming Language :: Python :: Implementation :: PyPy
Requires-Python: >=3.6.0
License-File: LICENSE.txt
Requires-Dist: numpy
Requires-Dist: opencv-python
Requires-Dist: pyueye
